<root>
	<info>
		<Author />
		<Black />
		<BlackTeam />
		<Date />
		<ECCO />
		<Event />
		<FEN>2b6/5k3/1r1aba3/5P1R1/9/9/9/9/4A4/2BK1A3 r - - 0 0</FEN>
		<Format>ICCS</Format>
		<Game>Chinese Chess</Game>
		<Opening />
		<PlayType>残局</PlayType>
		<RMKWriter />
		<Red />
		<RedTeam />
		<Result>红胜</Result>
		<Round />
		<Site />
		<Title>第5局</Title>
		<Variation />
		<Version>18</Version>
	</info>
	<moves>
		<m00 />
		<m01>f6f7
			<m01>h6h8</m01>
			<m02>f8f9</m02>
			<m03>f6f7</m03>
			<m04>e7g9</m04>
			<m05>f7f8</m05>
			<m06>f9e9</m06>
			<m07>h8h9</m07>
			<m08>e9d9</m08>
			<m09>h9g9</m09>
			<m10>d9d8</m10>
			<m11>g9e9</m11>
			<m12>b7b5</m12>
			<m13>f8e8</m13>红胜，但比主着法慢一步。
		</m01>冲兵入局，紧凑有力。
		<m02>f8e8</m02>只好回将，如果进退将，红方挥车速进。
		<m03>h6h8</m03>
		<m04>e8e9</m04>
		<m05>f7f8</m05>太监追皇帝，步步叫杀，不给黑方喘息机会。
		<m06>e9d9</m06>
		<m07>f8e8</m07>
		<m08>e7g9</m08>
		<m09>h8f8</m09>
		<m10>b7b5</m10>
		<m11>f8f9</m11>
	</moves>
</root>
