<root>
	<info>
		<Author />
		<Black />
		<BlackTeam />
		<Date />
		<ECCO />
		<Event />
		<FEN>2r1ka3/4a4/3P5/9/9/7R1/9/9/9/4K4 r - - 0 0</FEN>
		<Format>ICCS</Format>
		<Game>Chinese Chess</Game>
		<Opening />
		<PlayType>残局</PlayType>
		<RMKWriter />
		<Red />
		<RedTeam />
		<Result>红胜</Result>
		<Round />
		<Site />
		<Title>第6局</Title>
		<Variation />
		<Version>18</Version>
	</info>
	<moves>
		<m00 />这是车兵成杀的一种定式。
		<m01>d7d8</m01>乘黑车尚未抬头，冲兵攻士，伏千里照面，是入局的好着。
		<m02>c9c0</m02>
		<m03>e0e1</m03>
		<m04>c0d0
			<m04>c0f0</m04>
			<m05>h4b4</m05>速胜。
		</m04>
		<m05>d8e8</m05>
		<m06>e9d9</m06>
		<m07>e8e9</m07>
		<m08>d9d8</m08>
		<m09>e9f9</m09>
		<m10>d0d5</m10>
		<m11>h4e4</m11>及时占中，是取胜的关键。
		<m12>d5d6</m12>
		<m13>e4e8</m13>
		<m14>d8d7</m14>
		<m15>f9e9</m15>准备把兵从将后移过去，再沉车平杀。这种着法俗称小兵搜山。
		<m16>d6d5</m16>
		<m17>e9d9</m17>
		<m18>d5d4</m18>
		<m19>d9c9</m19>
		<m20>d4d5</m20>
		<m21>e8e9</m21>
		<m22>d7d8</m22>
		<m23>e9d9</m23>
	</moves>
</root>
